liberty/__init__.py
liberty/framework/__init__.py
liberty/framework/alembic.ini
liberty/framework/main.py
liberty/framework/alembic/README
liberty/framework/alembic/env.py
liberty/framework/alembic/script.py.mako
liberty/framework/alembic/versions/README
liberty/framework/business/__init__.py
liberty/framework/business/oracle.py
liberty/framework/business/postgres.py
liberty/framework/config/__init__.py
liberty/framework/config/files/liberty.ini
liberty/framework/controllers/__init__.py
liberty/framework/controllers/api_controller.py
liberty/framework/controllers/setup_controller.py
liberty/framework/controllers/socket_controller.py
liberty/framework/database/__init__.py
liberty/framework/database/base_dao.py
liberty/framework/database/ora_dao.py
liberty/framework/database/pg_dao.py
liberty/framework/logs/__init__.py
liberty/framework/models/__init__.py
liberty/framework/models/ai.py
liberty/framework/models/apidb.py
liberty/framework/models/applications.py
liberty/framework/models/auth.py
liberty/framework/models/base.py
liberty/framework/models/modules.py
liberty/framework/models/pool.py
liberty/framework/models/setup.py
liberty/framework/models/themes.py
liberty/framework/postgres/__init__.py
liberty/framework/postgres/dump/__init__.py
liberty/framework/postgres/dump/airflow.dump
liberty/framework/postgres/dump/gitea.dump
liberty/framework/postgres/dump/keycloak.dump
liberty/framework/postgres/dump/liberty.dump
liberty/framework/postgres/dump/libnarf.dump
liberty/framework/postgres/dump/libnjde.dump
liberty/framework/postgres/dump/libnsx1.dump
liberty/framework/postgres/dump/nomaarf.dump
liberty/framework/postgres/dump/nomajde.dump
liberty/framework/postgres/dump/nomasx1.dump
liberty/framework/public/__init__.py
liberty/framework/public/frontend/index.html
liberty/framework/public/frontend/assets/background_ly-VdfFMP8a.jpg
liberty/framework/public/frontend/assets/index-Ds3Hrec6.js
liberty/framework/public/frontend/assets/index-Ds3Hrec6.js.map
liberty_framework-6.0.81.dist-info/licenses/LICENSE.md
liberty_framework-6.0.81.dist-info/METADATA
liberty_framework-6.0.81.dist-info/WHEEL
liberty_framework-6.0.81.dist-info/entry_points.txt
liberty_framework-6.0.81.dist-info/top_level.txt
liberty_framework-6.0.81.dist-info/RECORD
