Metadata-Version: 2.4
Name: liberty-framework
Version: 6.0.81
Summary: Liberty Framework
Author: Franck Blettner
Author-email: franck.blettner@nomana-it.fr
Classifier: Programming Language :: Python :: 3
Classifier: Framework :: FastAPI
Classifier: Operating System :: OS Independent
Requires-Python: >=3.8
License-File: LICENSE.md
Requires-Dist: alembic==1.14.1
Requires-Dist: allure-pytest==2.13.5
Requires-Dist: allure-python-commons==2.13.5
Requires-Dist: annotated-types==0.7.0
Requires-Dist: anyio==4.8.0
Requires-Dist: asyncpg==0.30.0
Requires-Dist: attrs==25.1.0
Requires-Dist: bidict==0.23.1
Requires-Dist: certifi==2024.12.14
Requires-Dist: cffi==1.17.1
Requires-Dist: click==8.1.8
Requires-Dist: cryptography==44.0.0
Requires-Dist: dnspython==2.7.0
Requires-Dist: email_validator==2.2.0
Requires-Dist: fastapi==0.115.7
Requires-Dist: fastapi-cli==0.0.7
Requires-Dist: fastapi-socketio==0.0.10
Requires-Dist: greenlet==3.1.1
Requires-Dist: h11==0.14.0
Requires-Dist: httpcore==1.0.7
Requires-Dist: httptools==0.6.4
Requires-Dist: httpx==0.28.1
Requires-Dist: idna==3.10
Requires-Dist: inflect==7.5.0
Requires-Dist: iniconfig==2.0.0
Requires-Dist: Jinja2==3.1.5
Requires-Dist: Mako==1.3.8
Requires-Dist: markdown-it-py==3.0.0
Requires-Dist: MarkupSafe==3.0.2
Requires-Dist: mdurl==0.1.2
Requires-Dist: more-itertools==10.6.0
Requires-Dist: oracledb==2.4.1
Requires-Dist: packaging==24.2
Requires-Dist: pluggy==1.5.0
Requires-Dist: psycopg2-binary==2.9.10
Requires-Dist: pycparser==2.22
Requires-Dist: pydantic==2.10.6
Requires-Dist: pydantic_core==2.27.2
Requires-Dist: Pygments==2.19.1
Requires-Dist: PyJWT==2.10.1
Requires-Dist: pytest==8.3.4
Requires-Dist: python-dotenv==1.0.1
Requires-Dist: python-engineio==4.11.2
Requires-Dist: python-multipart==0.0.20
Requires-Dist: python-socketio==5.12.1
Requires-Dist: PyYAML==6.0.2
Requires-Dist: rich==13.9.4
Requires-Dist: rich-toolkit==0.13.2
Requires-Dist: setuptools==75.8.0
Requires-Dist: shellingham==1.5.4
Requires-Dist: simple-websocket==1.1.0
Requires-Dist: sniffio==1.3.1
Requires-Dist: SQLAlchemy==2.0.37
Requires-Dist: starlette==0.45.3
Requires-Dist: typeguard==4.4.1
Requires-Dist: typer==0.15.1
Requires-Dist: typing_extensions==4.12.2
Requires-Dist: uvicorn==0.34.0
Requires-Dist: uvloop==0.21.0
Requires-Dist: watchfiles==1.0.4
Requires-Dist: websockets==14.2
Requires-Dist: wsproto==1.2.0
Requires-Dist: build
Dynamic: author
Dynamic: author-email
Dynamic: classifier
Dynamic: description
Dynamic: description-content-type
Dynamic: license-file
Dynamic: requires-dist
Dynamic: requires-python
Dynamic: summary
